setup.py
abl/__init__.py
abl.robot.egg-info/PKG-INFO
abl.robot.egg-info/SOURCES.txt
abl.robot.egg-info/dependency_links.txt
abl.robot.egg-info/requires.txt
abl.robot.egg-info/top_level.txt
abl.robot.egg-info/zip-safe
abl/robot/__init__.py
abl/robot/base.py
abl/robot/mail.py
abl/robot/test.py