Metadata-Version: 1.0
Name: abl.robot
Version: 0.1.3
Summary: The Ableton Robot Framework, for writing daemons or commandline tools, with powerful features for error handling and logging.
Home-page: UNKNOWN
Author: Diez B. Roggisch
Author-email: diez.roggisch@ableton.com
License: MIT
Platform: UNKNOWN
Classifier: Development Status :: 5 - Production/Stable
Classifier: License :: OSI Approved :: MIT License
Classifier: Operating System :: OS Independent
Classifier: Programming Language :: Python
Classifier: Intended Audience :: Developers
